{
  "page_id": 1,
  "metadata": {
    "file_name": "doc_0025.png",
    "image_width": 777,
    "image_height": 1000
  },
  "lines": [
    {
      "text": "From:2A0",
      "bbox": [
        309,
        0,
        419,
        20
      ],
      "confidence": 0.8423103094100952
    },
    {
      "text": "Va:UMU",
      "bbox": [
        408,
        0,
        500,
        20
      ],
      "confidence": 0.9005136489868164
    },
    {
      "text": "OUIGOING MAIL",
      "bbox": [
        549,
        0,
        682,
        20
      ],
      "confidence": 0.9383894205093384
    },
    {
      "text": "CRC",
      "bbox": [
        53,
        13,
        169,
        71
      ],
      "confidence": 0.9991195201873779
    },
    {
      "text": "ox",
      "bbox": [
        653,
        17,
        674,
        28
      ],
      "confidence": 0.665474534034729
    },
    {
      "text": "To:",
      "bbox": [
        311,
        27,
        350,
        46
      ],
      "confidence": 0.9937687516212463
    },
    {
      "text": "CONTRACT",
      "bbox": [
        184,
        43,
        332,
        67
      ],
      "confidence": 0.999656081199646
    },
    {
      "text": "RESEARCH CÉNTERBVBA/SPAL",
      "bbox": [
        347,
        44,
        718,
        72
      ],
      "confidence": 0.9453229904174805
    },
    {
      "text": "B-1832 Zaventem",
      "bbox": [
        530,
        105,
        625,
        120
      ],
      "confidence": 0.9507184624671936
    },
    {
      "text": "(Sint-Stevens-Woluwe)",
      "bbox": [
        530,
        120,
        650,
        135
      ],
      "confidence": 0.9653846025466919
    },
    {
      "text": "INBIFO",
      "bbox": [
        68,
        130,
        133,
        149
      ],
      "confidence": 0.9816622734069824
    },
    {
      "text": "Tollaan / Avenue du Peage 101c",
      "bbox": [
        530,
        136,
        704,
        149
      ],
      "confidence": 0.9739335775375366
    },
    {
      "text": "Institut fur biologische Forschung",
      "bbox": [
        70,
        147,
        388,
        164
      ],
      "confidence": 0.9656691551208496
    },
    {
      "text": "Fuggerstrasse 3",
      "bbox": [
        68,
        162,
        215,
        180
      ],
      "confidence": 0.9498273134231567
    },
    {
      "text": "Teietoon/ Twephon 02/720:81 74",
      "bbox": [
        529,
        163,
        718,
        178
      ],
      "confidence": 0.8818489909172058
    },
    {
      "text": "Totelax / T41ax 02/725 12 00",
      "bbox": [
        529,
        178,
        695,
        195
      ],
      "confidence": 0.7622520327568054
    },
    {
      "text": "D-5000 K81n 90",
      "bbox": [
        70,
        195,
        203,
        209
      ],
      "confidence": 0.9801599383354187
    },
    {
      "text": "JGB/MCM",
      "bbox": [
        517,
        211,
        586,
        225
      ],
      "confidence": 0.9294158816337585
    },
    {
      "text": "PRQ_PORMA - (Studi• B6023)",
      "bbox": [
        68,
        253,
        313,
        270
      ],
      "confidence": 0.9198653697967529
    },
    {
      "text": "Zaventem, 23 Sep.91",
      "bbox": [
        517,
        255,
        695,
        269
      ],
      "confidence": 0.9818537831306458
    },
    {
      "text": "RECHNUNG NR: 29/91",
      "bbox": [
        67,
        266,
        240,
        285
      ],
      "confidence": 0.9405692219734192
    },
    {
      "text": "LFD.",
      "bbox": [
        68,
        299,
        108,
        315
      ],
      "confidence": 0.9840612411499023
    },
    {
      "text": "ANZAHL",
      "bbox": [
        123,
        298,
        183,
        316
      ],
      "confidence": 0.9531907439231873
    },
    {
      "text": "ARTIKKL",
      "bbox": [
        207,
        298,
        275,
        312
      ],
      "confidence": 0.9364220499992371
    },
    {
      "text": "PREIS",
      "bbox": [
        603,
        300,
        653,
        316
      ],
      "confidence": 0.9987810850143433
    },
    {
      "text": "NR.",
      "bbox": [
        68,
        316,
        95,
        331
      ],
      "confidence": 0.879126250743866
    },
    {
      "text": "(BP1",
      "bbox": [
        600,
        313,
        646,
        335
      ],
      "confidence": 0.7324223518371582
    },
    {
      "text": "Wert nur fur Sollgwecke bestimmt",
      "bbox": [
        298,
        342,
        605,
        361
      ],
      "confidence": 0.9551034569740295
    },
    {
      "text": "(waarde alleen voor douanedoeleinden)",
      "bbox": [
        300,
        357,
        652,
        377
      ],
      "confidence": 0.9906297922134399
    },
    {
      "text": "ROCKPRACHT VON VORUBERGKHKXDEX KXPORT",
      "bbox": [
        204,
        385,
        560,
        407
      ],
      "confidence": 0.9251806139945984
    },
    {
      "text": "(TERUGIKNDING VAN VOORLOPIG KXPORT)",
      "bbox": [
        205,
        401,
        538,
        424
      ],
      "confidence": 0.9428699016571045
    },
    {
      "text": "1",
      "bbox": [
        66,
        434,
        80,
        450
      ],
      "confidence": 0.999468982219696
    },
    {
      "text": "1",
      "bbox": [
        122,
        434,
        136,
        450
      ],
      "confidence": 0.9863539338111877
    },
    {
      "text": "Sartorius Waage U3600,",
      "bbox": [
        204,
        432,
        413,
        452
      ],
      "confidence": 0.984874963760376
    },
    {
      "text": "Fabr.-Nr. 36030092",
      "bbox": [
        205,
        451,
        376,
        465
      ],
      "confidence": 0.9914137721061707
    },
    {
      "text": "30.000,-",
      "bbox": [
        604,
        450,
        683,
        467
      ],
      "confidence": 0.9971596598625183
    },
    {
      "text": "2",
      "bbox": [
        66,
        479,
        80,
        495
      ],
      "confidence": 0.999942421913147
    },
    {
      "text": "· 1",
      "bbox": [
        113,
        478,
        136,
        495
      ],
      "confidence": 0.8098995685577393
    },
    {
      "text": "Pyroterm 8500, Thermometer ohne Fuhler",
      "bbox": [
        203,
        480,
        568,
        498
      ],
      "confidence": 0.9544683694839478
    },
    {
      "text": "10.000.-",
      "bbox": [
        603,
        481,
        685,
        498
      ],
      "confidence": 0.8665255904197693
    },
    {
      "text": "TOTAL:",
      "bbox": [
        515,
        510,
        577,
        529
      ],
      "confidence": 0.9972712397575378
    },
    {
      "text": "40.000,-",
      "bbox": [
        603,
        511,
        684,
        528
      ],
      "confidence": 0.9661914706230164
    },
    {
      "text": "DIESE PRO FORMA-RECHNUNG IST NUR PUR ZOLLZWECKE BESTIMMT:",
      "bbox": [
        59,
        598,
        608,
        623
      ],
      "confidence": 0.9746692776679993
    },
    {
      "text": "(DEZE PRO PORMA-FAKTUUR IS ALLEEN VOOR DOUANEDOELEINDEN BESTEMDI)",
      "bbox": [
        59,
        614,
        685,
        639
      ],
      "confidence": 0.9691980481147766
    },
    {
      "text": "cac",
      "bbox": [
        539,
        700,
        604,
        725
      ],
      "confidence": 0.8412278294563293
    },
    {
      "text": "Cortrac: Drcaa:ch Conter",
      "bbox": [
        541,
        720,
        706,
        739
      ],
      "confidence": 0.8735110759735107
    },
    {
      "text": "Tu.Jan",
      "bbox": [
        542,
        739,
        592,
        753
      ],
      "confidence": 0.8038337826728821
    },
    {
      "text": "juie:",
      "bbox": [
        596,
        738,
        631,
        752
      ],
      "confidence": 0.9442285299301147
    },
    {
      "text": "2028699749",
      "bbox": [
        723,
        736,
        760,
        888
      ],
      "confidence": 0.9998309016227722
    },
    {
      "text": "8 -1902",
      "bbox": [
        541,
        751,
        602,
        768
      ],
      "confidence": 0.8065261244773865
    },
    {
      "text": "(Zavontem",
      "bbox": [
        596,
        752,
        663,
        766
      ],
      "confidence": 0.8895902633666992
    }
  ],
  "full_text": "From:2A0\nVa:UMU\nOUIGOING MAIL\nCRC\nox\nTo:\nCONTRACT\nRESEARCH CÉNTERBVBA/SPAL\nB-1832 Zaventem\n(Sint-Stevens-Woluwe)\nINBIFO\nTollaan / Avenue du Peage 101c\nInstitut fur biologische Forschung\nFuggerstrasse 3\nTeietoon/ Twephon 02/720:81 74\nTotelax / T41ax 02/725 12 00\nD-5000 K81n 90\nJGB/MCM\nPRQ_PORMA - (Studi• B6023)\nZaventem, 23 Sep.91\nRECHNUNG NR: 29/91\nLFD.\nANZAHL\nARTIKKL\nPREIS\nNR.\n(BP1\nWert nur fur Sollgwecke bestimmt\n(waarde alleen voor douanedoeleinden)\nROCKPRACHT VON VORUBERGKHKXDEX KXPORT\n(TERUGIKNDING VAN VOORLOPIG KXPORT)\n1\n1\nSartorius Waage U3600,\nFabr.-Nr. 36030092\n30.000,-\n2\n· 1\nPyroterm 8500, Thermometer ohne Fuhler\n10.000.-\nTOTAL:\n40.000,-\nDIESE PRO FORMA-RECHNUNG IST NUR PUR ZOLLZWECKE BESTIMMT:\n(DEZE PRO PORMA-FAKTUUR IS ALLEEN VOOR DOUANEDOELEINDEN BESTEMDI)\ncac\nCortrac: Drcaa:ch Conter\nTu.Jan\njuie:\n2028699749\n8 -1902\n(Zavontem"
}