{
  "page_id": 1,
  "metadata": {
    "file_name": "doc_0233.png",
    "image_width": 754,
    "image_height": 1000
  },
  "lines": [
    {
      "text": "MRI1C",
      "bbox": [
        102,
        145,
        123,
        153
      ],
      "confidence": 0.6163462400436401
    },
    {
      "text": "339454",
      "bbox": [
        193,
        158,
        236,
        169
      ],
      "confidence": 0.8499736785888672
    },
    {
      "text": "AUTO RACING",
      "bbox": [
        68,
        315,
        168,
        337
      ],
      "confidence": 0.8966805934906006
    },
    {
      "text": "3324",
      "bbox": [
        94,
        309,
        146,
        321
      ],
      "confidence": 0.9805152416229248
    },
    {
      "text": "This season, Tracy's figured out how to win",
      "bbox": [
        66,
        336,
        657,
        382
      ],
      "confidence": 0.9903789758682251
    },
    {
      "text": "By Tim May",
      "bbox": [
        67,
        379,
        133,
        399
      ],
      "confidence": 0.9995502233505249
    },
    {
      "text": "The only thing the hoekey guy",
      "bbox": [
        302,
        379,
        480,
        402
      ],
      "confidence": 0.9583302140235901
    },
    {
      "text": "Dispatch Sponts Reponer",
      "bbox": [
        67,
        394,
        172,
        413
      ],
      "confidence": 0.930092453956604
    },
    {
      "text": "has going for him is that stick. Tracy",
      "bbox": [
        279,
        393,
        479,
        414
      ],
      "confidence": 0.9839525818824768
    },
    {
      "text": "and put myself in the position to",
      "bbox": [
        489,
        383,
        692,
        404
      ],
      "confidence": 0.9789042472839355
    },
    {
      "text": "have some bad luek,\" Tracy said.",
      "bbox": [
        490,
        397,
        692,
        416
      ],
      "confidence": 0.9587984085083008
    },
    {
      "text": "has neariy 800 horsepower in a",
      "bbox": [
        278,
        406,
        479,
        427
      ],
      "confidence": 0.9717496633529663
    },
    {
      "text": "\"But the middle and the end of the",
      "bbox": [
        489,
        409,
        692,
        431
      ],
      "confidence": 0.9816231727600098
    },
    {
      "text": "hard to imagine Paul Tracy assum-",
      "bbox": [
        66,
        427,
        267,
        448
      ],
      "confidence": 0.993886411190033
    },
    {
      "text": "In another life, it wouldn't be",
      "bbox": [
        90,
        413,
        266,
        431
      ],
      "confidence": 0.9934880137443542
    },
    {
      "text": "1,550-pound race car to do his bid-",
      "bbox": [
        277,
        418,
        478,
        440
      ],
      "confidence": 0.9596323370933533
    },
    {
      "text": "year have been great.",
      "bbox": [
        488,
        424,
        606,
        443
      ],
      "confidence": 0.9962196350097656
    },
    {
      "text": "ding. And he bids with an aggressive",
      "bbox": [
        277,
        431,
        478,
        453
      ],
      "confidence": 0.9815030694007874
    },
    {
      "text": "\"I've been able to fulfill most of",
      "bbox": [
        512,
        436,
        693,
        456
      ],
      "confidence": 0.9834541082382202
    },
    {
      "text": "ing the role of arsonist.",
      "bbox": [
        67,
        444,
        189,
        461
      ],
      "confidence": 0.9823417663574219
    },
    {
      "text": "But in this life he goes around",
      "bbox": [
        89,
        457,
        266,
        475
      ],
      "confidence": 0.9895667433738708
    },
    {
      "text": "flair.",
      "bbox": [
        277,
        446,
        305,
        462
      ],
      "confidence": 0.9884544014930725
    },
    {
      "text": "my goals, which was be in the top",
      "bbox": [
        488,
        451,
        692,
        471
      ],
      "confidence": 0.9757943749427795
    },
    {
      "text": "race,\" Tracy said. \"If a guy wants to",
      "bbox": [
        276,
        471,
        477,
        492
      ],
      "confidence": 0.9882991909980774
    },
    {
      "text": "\"I'm a competitor. I do like to",
      "bbox": [
        300,
        458,
        477,
        478
      ],
      "confidence": 0.9550471901893616
    },
    {
      "text": "five at the end of the season and win",
      "bbox": [
        488,
        464,
        692,
        484
      ],
      "confidence": 0.991777777671814
    },
    {
      "text": "with rosy cheeks, wire-rimmed",
      "bbox": [
        65,
        473,
        264,
        490
      ],
      "confidence": 0.9783319234848022
    },
    {
      "text": "get by me he's going to have to work",
      "bbox": [
        276,
        485,
        477,
        504
      ],
      "confidence": 0.9769111275672913
    },
    {
      "text": "some races. This Marlboro Penske",
      "bbox": [
        488,
        478,
        692,
        497
      ],
      "confidence": 0.9740764498710632
    },
    {
      "text": "glasses and a",
      "bbox": [
        65,
        488,
        154,
        502
      ],
      "confidence": 0.998123049736023
    },
    {
      "text": "soft-spoken de-",
      "bbox": [
        66,
        501,
        154,
        515
      ],
      "confidence": 0.9996051788330078
    },
    {
      "text": "hard to do it. Ever since I was a kid,",
      "bbox": [
        276,
        497,
        477,
        517
      ],
      "confidence": 0.9502388834953308
    },
    {
      "text": "team, we've challenged for the lead",
      "bbox": [
        488,
        491,
        691,
        509
      ],
      "confidence": 0.981508731842041
    },
    {
      "text": "meanor. The",
      "bbox": [
        65,
        513,
        154,
        529
      ],
      "confidence": 0.9932651519775391
    },
    {
      "text": "that's the way I'e always raced.\"",
      "bbox": [
        277,
        510,
        456,
        529
      ],
      "confidence": 0.9660841226577759
    },
    {
      "text": "at almost every track we've been to.\"",
      "bbox": [
        488,
        504,
        686,
        522
      ],
      "confidence": 0.9722010493278503
    },
    {
      "text": "There have been races the sec-",
      "bbox": [
        511,
        517,
        691,
        536
      ],
      "confidence": 0.9993191957473755
    },
    {
      "text": "fire is hidden.",
      "bbox": [
        65,
        526,
        152,
        542
      ],
      "confidence": 0.9918704628944397
    },
    {
      "text": "Except there has been a noti-",
      "bbox": [
        299,
        524,
        477,
        542
      ],
      "confidence": 0.9708207249641418
    },
    {
      "text": "ond half of the season in which he",
      "bbox": [
        487,
        529,
        691,
        549
      ],
      "confidence": 0.9674085974693298
    },
    {
      "text": "Obscured by",
      "bbox": [
        64,
        538,
        153,
        558
      ],
      "confidence": 0.9594992995262146
    },
    {
      "text": "ceable change in Tracy's style this",
      "bbox": [
        276,
        536,
        476,
        556
      ],
      "confidence": 0.9824180603027344
    },
    {
      "text": "has appeared invincible in the",
      "bbox": [
        487,
        543,
        690,
        563
      ],
      "confidence": 0.9955129623413086
    },
    {
      "text": "the visor of his",
      "bbox": [
        65,
        554,
        152,
        569
      ],
      "confidence": 0.9696197509765625
    },
    {
      "text": "year. Oh, he's still fast and fearless,",
      "bbox": [
        275,
        549,
        476,
        569
      ],
      "confidence": 0.98369961977005
    },
    {
      "text": "demonically so at times.",
      "bbox": [
        277,
        562,
        403,
        579
      ],
      "confidence": 0.9962615966796875
    },
    {
      "text": "Penske car.",
      "bbox": [
        486,
        555,
        553,
        576
      ],
      "confidence": 0.9924585223197937
    },
    {
      "text": "full-face racing",
      "bbox": [
        63,
        565,
        153,
        585
      ],
      "confidence": 0.9982682466506958
    },
    {
      "text": "But last year, when he drove",
      "bbox": [
        298,
        573,
        476,
        594
      ],
      "confidence": 0.9642359614372253
    },
    {
      "text": "\"I wouldn't say invincible, but",
      "bbox": [
        509,
        568,
        689,
        589
      ],
      "confidence": 0.9832125306129456
    },
    {
      "text": "fests itself in",
      "bbox": [
        63,
        591,
        151,
        610
      ],
      "confidence": 0.9767025709152222
    },
    {
      "text": "helmet, it mani-",
      "bbox": [
        64,
        580,
        152,
        597
      ],
      "confidence": 0.964281439781189
    },
    {
      "text": "most of the season in relief of the",
      "bbox": [
        275,
        586,
        476,
        607
      ],
      "confidence": 0.9662169218063354
    },
    {
      "text": "there is the feeling of, when I get out",
      "bbox": [
        487,
        582,
        690,
        602
      ],
      "confidence": 0.972582221031189
    },
    {
      "text": "his right foot 16",
      "bbox": [
        62,
        605,
        151,
        624
      ],
      "confidence": 0.9960534572601318
    },
    {
      "text": "injured Rick Mears, fast laps, spee-",
      "bbox": [
        275,
        599,
        476,
        620
      ],
      "confidence": 0.9728028774261475
    },
    {
      "text": "of the car after a qualifying session,",
      "bbox": [
        487,
        595,
        689,
        615
      ],
      "confidence": 0.9703178405761719
    },
    {
      "text": "Sunday after-",
      "bbox": [
        63,
        620,
        151,
        637
      ],
      "confidence": 0.9740263223648071
    },
    {
      "text": "tacular crashes and no wins pretty",
      "bbox": [
        274,
        612,
        475,
        634
      ],
      "confidence": 0.992462158203125
    },
    {
      "text": "if I'm not one of the two or three",
      "bbox": [
        486,
        609,
        689,
        628
      ],
      "confidence": 0.9721090793609619
    },
    {
      "text": "noons a year.",
      "bbox": [
        63,
        636,
        135,
        650
      ],
      "confidence": 0.9985523223876953
    },
    {
      "text": "well summed up the venture.",
      "bbox": [
        274,
        626,
        430,
        645
      ],
      "confidence": 0.9988222718238831
    },
    {
      "text": "quickest guys, I'm not very happy",
      "bbox": [
        486,
        623,
        689,
        643
      ],
      "confidence": 0.9817464351654053
    },
    {
      "text": "about it,\" Tracy said.",
      "bbox": [
        487,
        637,
        602,
        654
      ],
      "confidence": 0.9495782256126404
    },
    {
      "text": "Seated in",
      "bbox": [
        85,
        645,
        150,
        665
      ],
      "confidence": 0.9609577655792236
    },
    {
      "text": "Paul Tracy",
      "bbox": [
        162,
        638,
        226,
        655
      ],
      "confidence": 0.9996724128723145
    },
    {
      "text": "this year on the mile oval at Phoenix",
      "bbox": [
        273,
        651,
        475,
        671
      ],
      "confidence": 0.96254563331604
    },
    {
      "text": "Since blowing the second race",
      "bbox": [
        297,
        639,
        476,
        658
      ],
      "confidence": 0.9717832803726196
    },
    {
      "text": "That's the kind of attitude team",
      "bbox": [
        509,
        649,
        689,
        668
      ],
      "confidence": 0.9875263571739197
    },
    {
      "text": "one of the Mariboro Penske-Chevy",
      "bbox": [
        61,
        657,
        263,
        676
      ],
      "confidence": 0.960479736328125
    },
    {
      "text": "— he had a huge lead but lost eontrol",
      "bbox": [
        273,
        664,
        475,
        685
      ],
      "confidence": 0.9597831964492798
    },
    {
      "text": "owner Roger Penske appreciates.",
      "bbox": [
        486,
        662,
        689,
        683
      ],
      "confidence": 0.9927971363067627
    },
    {
      "text": "IndyCars, Paul Tracy, 24, is a totally",
      "bbox": [
        63,
        674,
        261,
        689
      ],
      "confidence": 0.9837996959686279
    },
    {
      "text": "and crashed while losing patience",
      "bbox": [
        272,
        677,
        476,
        698
      ],
      "confidence": 0.9943976998329163
    },
    {
      "text": "That's one of the reasons a rumor",
      "bbox": [
        486,
        675,
        690,
        696
      ],
      "confidence": 0.9828734993934631
    },
    {
      "text": "different person.",
      "bbox": [
        61,
        684,
        149,
        705
      ],
      "confidence": 0.9968351721763611
    },
    {
      "text": "with a slower car - Tracy has won",
      "bbox": [
        272,
        691,
        476,
        711
      ],
      "confidence": 0.9762265682220459
    },
    {
      "text": "earlier in the season seemed so pre-",
      "bbox": [
        486,
        689,
        689,
        710
      ],
      "confidence": 0.9802022576332092
    },
    {
      "text": "helmet on,\" Tracy said as he pre-",
      "bbox": [
        61,
        712,
        261,
        731
      ],
      "confidence": 0.9831957817077637
    },
    {
      "text": "\"I am no nice guy when I put the",
      "bbox": [
        85,
        700,
        261,
        717
      ],
      "confidence": 0.9640522599220276
    },
    {
      "text": "three times.",
      "bbox": [
        272,
        703,
        340,
        723
      ],
      "confidence": 0.996682345867157
    },
    {
      "text": "posterous: Penske was not going to",
      "bbox": [
        486,
        703,
        690,
        724
      ],
      "confidence": 0.9769648313522339
    },
    {
      "text": "pared to begin practice today for",
      "bbox": [
        61,
        725,
        261,
        744
      ],
      "confidence": 0.9787367582321167
    },
    {
      "text": "He goes into preliminary quali-",
      "bbox": [
        295,
        718,
        474,
        736
      ],
      "confidence": 0.9818838238716125
    },
    {
      "text": "exercise his option to re-sign Tracy,",
      "bbox": [
        485,
        717,
        689,
        737
      ],
      "confidence": 0.98320472240448
    },
    {
      "text": "Sunday's Pioncer 200 at Mid-Ohio",
      "bbox": [
        61,
        737,
        260,
        756
      ],
      "confidence": 0.9768252968788147
    },
    {
      "text": "fying for the Pioneer 'J0 tod as",
      "bbox": [
        272,
        730,
        475,
        750
      ],
      "confidence": 0.9593483805656433
    },
    {
      "text": "a driver he has d. cxoped from Indy-",
      "bbox": [
        485,
        730,
        688,
        750
      ],
      "confidence": 0.9368290305137634
    },
    {
      "text": "Sports Car Course. \"It's something",
      "bbox": [
        60,
        750,
        260,
        771
      ],
      "confidence": 0.9684145450592041
    },
    {
      "text": "season points standirgs behind Ni-",
      "bbox": [
        271,
        757,
        474,
        775
      ],
      "confidence": 0.971117377281189
    },
    {
      "text": "one of the major players, third in the",
      "bbox": [
        272,
        744,
        473,
        762
      ],
      "confidence": 0.9912775158882141
    },
    {
      "text": "Car infancy three years ago.",
      "bbox": [
        485,
        744,
        641,
        763
      ],
      "confidence": 0.9864674806594849
    },
    {
      "text": "\"I heard a lot of those rumors,",
      "bbox": [
        509,
        757,
        688,
        778
      ],
      "confidence": 0.97396320104599
    },
    {
      "text": "like a split image. I turm into a",
      "bbox": [
        59,
        763,
        260,
        784
      ],
      "confidence": 0.9739513993263245
    },
    {
      "text": "gel Mansell and Penske Racing",
      "bbox": [
        271,
        769,
        473,
        789
      ],
      "confidence": 0.9589518904685974
    },
    {
      "text": "and I'd listen and laugh,\" Tracy said.",
      "bbox": [
        485,
        770,
        687,
        791
      ],
      "confidence": 0.9683563113212585
    },
    {
      "text": "different person, much different",
      "bbox": [
        59,
        775,
        259,
        799
      ],
      "confidence": 0.9700207114219666
    },
    {
      "text": "teammate Emerson Fittipaldi.",
      "bbox": [
        271,
        782,
        433,
        800
      ],
      "confidence": 0.9986408352851868
    },
    {
      "text": "\"I knew I was planning on staying",
      "bbox": [
        485,
        782,
        688,
        807
      ],
      "confidence": 0.9494909644126892
    },
    {
      "text": "around talking with the crew, or",
      "bbox": [
        58,
        802,
        259,
        825
      ],
      "confidence": 0.9858846068382263
    },
    {
      "text": "from the way I am when I'm sitting",
      "bbox": [
        59,
        788,
        259,
        812
      ],
      "confidence": 0.9986401796340942
    },
    {
      "text": "The first part of the year was",
      "bbox": [
        293,
        794,
        474,
        815
      ],
      "confidence": 0.9822242856025696
    },
    {
      "text": "with Roger Penske. ... We have re-",
      "bbox": [
        483,
        794,
        688,
        821
      ],
      "confidence": 0.9368141889572144
    },
    {
      "text": "reporters, or fans.",
      "bbox": [
        59,
        814,
        155,
        836
      ],
      "confidence": 0.9716324806213379
    },
    {
      "text": "pretty tough. I had a lot of bad huck",
      "bbox": [
        271,
        811,
        471,
        826
      ],
      "confidence": 0.961486279964447
    },
    {
      "text": "signed through the '95 season.\"",
      "bbox": [
        484,
        811,
        652,
        831
      ],
      "confidence": 0.972519040107727
    },
    {
      "text": "\"I think that's the way you have",
      "bbox": [
        81,
        827,
        258,
        852
      ],
      "confidence": 0.9505195617675781
    },
    {
      "text": "to be in any spart, whether you're",
      "bbox": [
        58,
        841,
        258,
        864
      ],
      "confidence": 0.9883851408958435
    },
    {
      "text": "putting on a racing helmet or a",
      "bbox": [
        58,
        854,
        259,
        878
      ],
      "confidence": 0.9964607954025269
    },
    {
      "text": "hoekey helmet.\"",
      "bbox": [
        57,
        866,
        143,
        887
      ],
      "confidence": 0.9681364297866821
    }
  ],
  "full_text": "MRI1C\n339454\nAUTO RACING\n3324\nThis season, Tracy's figured out how to win\nBy Tim May\nThe only thing the hoekey guy\nDispatch Sponts Reponer\nhas going for him is that stick. Tracy\nand put myself in the position to\nhave some bad luek,\" Tracy said.\nhas neariy 800 horsepower in a\n\"But the middle and the end of the\nhard to imagine Paul Tracy assum-\nIn another life, it wouldn't be\n1,550-pound race car to do his bid-\nyear have been great.\nding. And he bids with an aggressive\n\"I've been able to fulfill most of\ning the role of arsonist.\nBut in this life he goes around\nflair.\nmy goals, which was be in the top\nrace,\" Tracy said. \"If a guy wants to\n\"I'm a competitor. I do like to\nfive at the end of the season and win\nwith rosy cheeks, wire-rimmed\nget by me he's going to have to work\nsome races. This Marlboro Penske\nglasses and a\nsoft-spoken de-\nhard to do it. Ever since I was a kid,\nteam, we've challenged for the lead\nmeanor. The\nthat's the way I'e always raced.\"\nat almost every track we've been to.\"\nThere have been races the sec-\nfire is hidden.\nExcept there has been a noti-\nond half of the season in which he\nObscured by\nceable change in Tracy's style this\nhas appeared invincible in the\nthe visor of his\nyear. Oh, he's still fast and fearless,\ndemonically so at times.\nPenske car.\nfull-face racing\nBut last year, when he drove\n\"I wouldn't say invincible, but\nfests itself in\nhelmet, it mani-\nmost of the season in relief of the\nthere is the feeling of, when I get out\nhis right foot 16\ninjured Rick Mears, fast laps, spee-\nof the car after a qualifying session,\nSunday after-\ntacular crashes and no wins pretty\nif I'm not one of the two or three\nnoons a year.\nwell summed up the venture.\nquickest guys, I'm not very happy\nabout it,\" Tracy said.\nSeated in\nPaul Tracy\nthis year on the mile oval at Phoenix\nSince blowing the second race\nThat's the kind of attitude team\none of the Mariboro Penske-Chevy\n— he had a huge lead but lost eontrol\nowner Roger Penske appreciates.\nIndyCars, Paul Tracy, 24, is a totally\nand crashed while losing patience\nThat's one of the reasons a rumor\ndifferent person.\nwith a slower car - Tracy has won\nearlier in the season seemed so pre-\nhelmet on,\" Tracy said as he pre-\n\"I am no nice guy when I put the\nthree times.\nposterous: Penske was not going to\npared to begin practice today for\nHe goes into preliminary quali-\nexercise his option to re-sign Tracy,\nSunday's Pioncer 200 at Mid-Ohio\nfying for the Pioneer 'J0 tod as\na driver he has d. cxoped from Indy-\nSports Car Course. \"It's something\nseason points standirgs behind Ni-\none of the major players, third in the\nCar infancy three years ago.\n\"I heard a lot of those rumors,\nlike a split image. I turm into a\ngel Mansell and Penske Racing\nand I'd listen and laugh,\" Tracy said.\ndifferent person, much different\nteammate Emerson Fittipaldi.\n\"I knew I was planning on staying\naround talking with the crew, or\nfrom the way I am when I'm sitting\nThe first part of the year was\nwith Roger Penske. ... We have re-\nreporters, or fans.\npretty tough. I had a lot of bad huck\nsigned through the '95 season.\"\n\"I think that's the way you have\nto be in any spart, whether you're\nputting on a racing helmet or a\nhoekey helmet.\""
}